mass_database/__init__.py
mass_database-0.0.3.dist-info/LICENSE
mass_database-0.0.3.dist-info/METADATA
mass_database-0.0.3.dist-info/WHEEL
mass_database-0.0.3.dist-info/top_level.txt
mass_database-0.0.3.dist-info/zip-safe
mass_database-0.0.3.dist-info/RECORD
